trevorfrench/__init__.py
trevorfrench/stats.py
trevorfrench-0.0.3.dist-info/METADATA
trevorfrench-0.0.3.dist-info/WHEEL
trevorfrench-0.0.3.dist-info/licenses/LICENSE
trevorfrench-0.0.3.dist-info/RECORD
