Metadata-Version: 2.1
Name: trevorfrench
Version: 0.0.3
Summary: A personal package.
Project-URL: Homepage, https://github.com/TrevorFrench/trevorfrench_python
Project-URL: Bug Tracker, https://github.com/TrevorFrench/trevorfrench_python
Author-email: Trevor French <FrenchTrevor@outlook.com>
License: Copyright (c) 2018 The Python Packaging Authority
Classifier: License :: OSI Approved :: MIT License
Classifier: Operating System :: OS Independent
Classifier: Programming Language :: Python :: 3
Requires-Python: >=3.7
